{
    "sourceFile": "apps/admin_web/lib/admin_web/templates/layout/_side.html.heex",
    "activeCommit": 0,
    "commits": [
        {
            "activePatchIndex": 27,
            "patches": [
                {
                    "date": 1657804231876,
                    "content": "Index: \n===================================================================\n--- \n+++ \n"
                },
                {
                    "date": 1657804291586,
                    "content": "Index: \n===================================================================\n--- \n+++ \n@@ -24,22 +24,11 @@\n             </form>\n           </li>\n           <li>\n             <%= link to: Routes.page_path(@conn, :index), class: \"text-base text-gray-900 font-normal rounded-lg flex items-center p-2 hover:bg-gray-100 group\" do %>\n-                <span class=\"self-center whitespace-nowrap\">\n-                    <span class=\"text-amber-500\">Optimal</span>\n-                    <span>Finder</span>\n-                </span>\n+              <Heroicons.Outline.x /> \n+              <span class=\"ml-3\">Dashboard</span>\n             <% end %>\n-            <a href=\"https://demo.themesberg.com/windster/\"\n-              class=\"text-base text-gray-900 font-normal rounded-lg flex items-center p-2 hover:bg-gray-100 group\">\n-              <svg class=\"w-6 h-6 text-gray-500 group-hover:text-gray-900 transition duration-75\" fill=\"currentColor\"\n-                viewBox=\"0 0 20 20\" xmlns=\"http://www.w3.org/2000/svg\">\n-                <path d=\"M2 10a8 8 0 018-8v8h8a8 8 0 11-16 0z\"></path>\n-                <path d=\"M12 2.252A8.014 8.014 0 0117.748 8H12V2.252z\"></path>\n-              </svg>\n-              <span class=\"ml-3\">Dashboard</span>\n-            </a>\n           </li>\n           <li>\n             <a href=\"https://demo.themesberg.com/windster-pro/kanban/\" target=\"_blank\"\n               class=\"text-base text-gray-900 font-normal rounded-lg hover:bg-gray-100 flex items-center p-2 group \">\n"
                },
                {
                    "date": 1657804363223,
                    "content": "Index: \n===================================================================\n--- \n+++ \n@@ -24,9 +24,9 @@\n             </form>\n           </li>\n           <li>\n             <%= link to: Routes.page_path(@conn, :index), class: \"text-base text-gray-900 font-normal rounded-lg flex items-center p-2 hover:bg-gray-100 group\" do %>\n-              <Heroicons.Outline.x /> \n+              <Heroicons.Outline.chart_pie />\n               <span class=\"ml-3\">Dashboard</span>\n             <% end %>\n           </li>\n           <li>\n"
                },
                {
                    "date": 1657804373786,
                    "content": "Index: \n===================================================================\n--- \n+++ \n@@ -24,9 +24,9 @@\n             </form>\n           </li>\n           <li>\n             <%= link to: Routes.page_path(@conn, :index), class: \"text-base text-gray-900 font-normal rounded-lg flex items-center p-2 hover:bg-gray-100 group\" do %>\n-              <Heroicons.Outline.chart_pie />\n+              <Heroicons.Solid.chart_pie />\n               <span class=\"ml-3\">Dashboard</span>\n             <% end %>\n           </li>\n           <li>\n"
                },
                {
                    "date": 1657804403588,
                    "content": "Index: \n===================================================================\n--- \n+++ \n@@ -24,9 +24,9 @@\n             </form>\n           </li>\n           <li>\n             <%= link to: Routes.page_path(@conn, :index), class: \"text-base text-gray-900 font-normal rounded-lg flex items-center p-2 hover:bg-gray-100 group\" do %>\n-              <Heroicons.Solid.chart_pie />\n+              <Heroicons.Outline.chart_pie />\n               <span class=\"ml-3\">Dashboard</span>\n             <% end %>\n           </li>\n           <li>\n"
                },
                {
                    "date": 1657810082325,
                    "content": "Index: \n===================================================================\n--- \n+++ \n@@ -23,9 +23,9 @@\n               </div>\n             </form>\n           </li>\n           <li>\n-            <%= link to: Routes.page_path(@conn, :index), class: \"text-base text-gray-900 font-normal rounded-lg flex items-center p-2 hover:bg-gray-100 group\" do %>\n+            <%= link to: Routes.page_path(@conn, :index), class: \"sidebar-link\" do %>\n               <Heroicons.Outline.chart_pie />\n               <span class=\"ml-3\">Dashboard</span>\n             <% end %>\n           </li>\n"
                },
                {
                    "date": 1657811725470,
                    "content": "Index: \n===================================================================\n--- \n+++ \n@@ -23,9 +23,9 @@\n               </div>\n             </form>\n           </li>\n           <li>\n-            <%= link to: Routes.page_path(@conn, :index), class: \"sidebar-link\" do %>\n+            <%= link to: Routes.page_path(@conn, :index), class: \"text-base text-gray-900 font-normal rounded-lg flex items-center p-2 hover:bg-gray-100 group\" do %>\n               <Heroicons.Outline.chart_pie />\n               <span class=\"ml-3\">Dashboard</span>\n             <% end %>\n           </li>\n"
                },
                {
                    "date": 1657827532705,
                    "content": "Index: \n===================================================================\n--- \n+++ \n@@ -23,9 +23,9 @@\n               </div>\n             </form>\n           </li>\n           <li>\n-            <%= link to: Routes.page_path(@conn, :index), class: \"text-base text-gray-900 font-normal rounded-lg flex items-center p-2 hover:bg-gray-100 group\" do %>\n+            <%= link to: Routes.page_path(@conn, :index), class: \"text-base text-gray-900 font-normal rounded-lg hover:bg-gray-100 flex items-center p-2 group\" do %>\n               <Heroicons.Outline.chart_pie />\n               <span class=\"ml-3\">Dashboard</span>\n             <% end %>\n           </li>\n"
                },
                {
                    "date": 1657827725654,
                    "content": "Index: \n===================================================================\n--- \n+++ \n@@ -24,9 +24,9 @@\n             </form>\n           </li>\n           <li>\n             <%= link to: Routes.page_path(@conn, :index), class: \"text-base text-gray-900 font-normal rounded-lg hover:bg-gray-100 flex items-center p-2 group\" do %>\n-              <Heroicons.Outline.chart_pie />\n+              <Heroicons.Outline.chart_pie class=\"w-6 h-6 text-gray-500 flex-shrink-0 group-hover:text-gray-900 transition duration-75\" />\n               <span class=\"ml-3\">Dashboard</span>\n             <% end %>\n           </li>\n           <li>\n"
                },
                {
                    "date": 1657830730715,
                    "content": "Index: \n===================================================================\n--- \n+++ \n@@ -22,9 +22,17 @@\n                   placeholder=\"Search\">\n               </div>\n             </form>\n           </li>\n+          <% for m <- @menu() do %>\n           <li>\n+            <%= link to: m.route, class: \"text-base text-gray-900 font-normal rounded-lg hover:bg-gray-100 flex items-center p-2 group\" do %>\n+              <Heroicons.Outline.chart_pie class=\"w-6 h-6 text-gray-500 flex-shrink-0 group-hover:text-gray-900 transition duration-75\" />\n+              <span class=\"ml-3\"><%= m.label %></span>\n+            <% end %>\n+          </li>\n+          <% end %>\n+          <li>\n             <%= link to: Routes.page_path(@conn, :index), class: \"text-base text-gray-900 font-normal rounded-lg hover:bg-gray-100 flex items-center p-2 group\" do %>\n               <Heroicons.Outline.chart_pie class=\"w-6 h-6 text-gray-500 flex-shrink-0 group-hover:text-gray-900 transition duration-75\" />\n               <span class=\"ml-3\">Dashboard</span>\n             <% end %>\n"
                },
                {
                    "date": 1657830753771,
                    "content": "Index: \n===================================================================\n--- \n+++ \n@@ -22,9 +22,9 @@\n                   placeholder=\"Search\">\n               </div>\n             </form>\n           </li>\n-          <% for m <- @menu() do %>\n+          <% for m <- @menu do %>\n           <li>\n             <%= link to: m.route, class: \"text-base text-gray-900 font-normal rounded-lg hover:bg-gray-100 flex items-center p-2 group\" do %>\n               <Heroicons.Outline.chart_pie class=\"w-6 h-6 text-gray-500 flex-shrink-0 group-hover:text-gray-900 transition duration-75\" />\n               <span class=\"ml-3\"><%= m.label %></span>\n"
                },
                {
                    "date": 1657830810535,
                    "content": "Index: \n===================================================================\n--- \n+++ \n@@ -25,9 +25,9 @@\n           </li>\n           <% for m <- @menu do %>\n           <li>\n             <%= link to: m.route, class: \"text-base text-gray-900 font-normal rounded-lg hover:bg-gray-100 flex items-center p-2 group\" do %>\n-              <Heroicons.Outline.chart_pie class=\"w-6 h-6 text-gray-500 flex-shrink-0 group-hover:text-gray-900 transition duration-75\" />\n+              <Heroicons.Outline.render icon=\"{m.icon}\" class=\"w-6 h-6 text-gray-500 flex-shrink-0 group-hover:text-gray-900 transition duration-75\" />\n               <span class=\"ml-3\"><%= m.label %></span>\n             <% end %>\n           </li>\n           <% end %>\n"
                },
                {
                    "date": 1657830870593,
                    "content": "Index: \n===================================================================\n--- \n+++ \n@@ -22,9 +22,9 @@\n                   placeholder=\"Search\">\n               </div>\n             </form>\n           </li>\n-          <% for m <- @menu do %>\n+          <% for m <- menu() do %>\n           <li>\n             <%= link to: m.route, class: \"text-base text-gray-900 font-normal rounded-lg hover:bg-gray-100 flex items-center p-2 group\" do %>\n               <Heroicons.Outline.render icon=\"{m.icon}\" class=\"w-6 h-6 text-gray-500 flex-shrink-0 group-hover:text-gray-900 transition duration-75\" />\n               <span class=\"ml-3\"><%= m.label %></span>\n"
                },
                {
                    "date": 1657831286316,
                    "content": "Index: \n===================================================================\n--- \n+++ \n@@ -22,9 +22,9 @@\n                   placeholder=\"Search\">\n               </div>\n             </form>\n           </li>\n-          <% for m <- menu() do %>\n+          <%= for m <- menu() do %>\n           <li>\n             <%= link to: m.route, class: \"text-base text-gray-900 font-normal rounded-lg hover:bg-gray-100 flex items-center p-2 group\" do %>\n               <Heroicons.Outline.render icon=\"{m.icon}\" class=\"w-6 h-6 text-gray-500 flex-shrink-0 group-hover:text-gray-900 transition duration-75\" />\n               <span class=\"ml-3\"><%= m.label %></span>\n"
                },
                {
                    "date": 1657831297844,
                    "content": "Index: \n===================================================================\n--- \n+++ \n@@ -22,9 +22,9 @@\n                   placeholder=\"Search\">\n               </div>\n             </form>\n           </li>\n-          <%= for m <- menu() do %>\n+          <%= for m <- @menu() do %>\n           <li>\n             <%= link to: m.route, class: \"text-base text-gray-900 font-normal rounded-lg hover:bg-gray-100 flex items-center p-2 group\" do %>\n               <Heroicons.Outline.render icon=\"{m.icon}\" class=\"w-6 h-6 text-gray-500 flex-shrink-0 group-hover:text-gray-900 transition duration-75\" />\n               <span class=\"ml-3\"><%= m.label %></span>\n"
                },
                {
                    "date": 1657831319911,
                    "content": "Index: \n===================================================================\n--- \n+++ \n@@ -22,9 +22,9 @@\n                   placeholder=\"Search\">\n               </div>\n             </form>\n           </li>\n-          <%= for m <- @menu() do %>\n+          <%= for m <- menu() do %>\n           <li>\n             <%= link to: m.route, class: \"text-base text-gray-900 font-normal rounded-lg hover:bg-gray-100 flex items-center p-2 group\" do %>\n               <Heroicons.Outline.render icon=\"{m.icon}\" class=\"w-6 h-6 text-gray-500 flex-shrink-0 group-hover:text-gray-900 transition duration-75\" />\n               <span class=\"ml-3\"><%= m.label %></span>\n"
                },
                {
                    "date": 1657831344416,
                    "content": "Index: \n===================================================================\n--- \n+++ \n@@ -23,8 +23,9 @@\n               </div>\n             </form>\n           </li>\n           <%= for m <- menu() do %>\n+          <%= inspect m %>\n           <li>\n             <%= link to: m.route, class: \"text-base text-gray-900 font-normal rounded-lg hover:bg-gray-100 flex items-center p-2 group\" do %>\n               <Heroicons.Outline.render icon=\"{m.icon}\" class=\"w-6 h-6 text-gray-500 flex-shrink-0 group-hover:text-gray-900 transition duration-75\" />\n               <span class=\"ml-3\"><%= m.label %></span>\n"
                },
                {
                    "date": 1657831362370,
                    "content": "Index: \n===================================================================\n--- \n+++ \n@@ -22,10 +22,10 @@\n                   placeholder=\"Search\">\n               </div>\n             </form>\n           </li>\n+          <%= inspect menu() %>\n           <%= for m <- menu() do %>\n-          <%= inspect m %>\n           <li>\n             <%= link to: m.route, class: \"text-base text-gray-900 font-normal rounded-lg hover:bg-gray-100 flex items-center p-2 group\" do %>\n               <Heroicons.Outline.render icon=\"{m.icon}\" class=\"w-6 h-6 text-gray-500 flex-shrink-0 group-hover:text-gray-900 transition duration-75\" />\n               <span class=\"ml-3\"><%= m.label %></span>\n"
                },
                {
                    "date": 1657832063693,
                    "content": "Index: \n===================================================================\n--- \n+++ \n@@ -26,9 +26,9 @@\n           <%= inspect menu() %>\n           <%= for m <- menu() do %>\n           <li>\n             <%= link to: m.route, class: \"text-base text-gray-900 font-normal rounded-lg hover:bg-gray-100 flex items-center p-2 group\" do %>\n-              <Heroicons.Outline.render icon=\"{m.icon}\" class=\"w-6 h-6 text-gray-500 flex-shrink-0 group-hover:text-gray-900 transition duration-75\" />\n+              <Heroicons.Outline.render icon=\"{m[:icon]}\" class=\"w-6 h-6 text-gray-500 flex-shrink-0 group-hover:text-gray-900 transition duration-75\" />\n               <span class=\"ml-3\"><%= m.label %></span>\n             <% end %>\n           </li>\n           <% end %>\n"
                },
                {
                    "date": 1657832078028,
                    "content": "Index: \n===================================================================\n--- \n+++ \n@@ -26,9 +26,9 @@\n           <%= inspect menu() %>\n           <%= for m <- menu() do %>\n           <li>\n             <%= link to: m.route, class: \"text-base text-gray-900 font-normal rounded-lg hover:bg-gray-100 flex items-center p-2 group\" do %>\n-              <Heroicons.Outline.render icon=\"{m[:icon]}\" class=\"w-6 h-6 text-gray-500 flex-shrink-0 group-hover:text-gray-900 transition duration-75\" />\n+              <Heroicons.Outline.render icon=\"{m.icon}\" class=\"w-6 h-6 text-gray-500 flex-shrink-0 group-hover:text-gray-900 transition duration-75\" />\n               <span class=\"ml-3\"><%= m.label %></span>\n             <% end %>\n           </li>\n           <% end %>\n"
                },
                {
                    "date": 1657832223713,
                    "content": "Index: \n===================================================================\n--- \n+++ \n@@ -26,9 +26,9 @@\n           <%= inspect menu() %>\n           <%= for m <- menu() do %>\n           <li>\n             <%= link to: m.route, class: \"text-base text-gray-900 font-normal rounded-lg hover:bg-gray-100 flex items-center p-2 group\" do %>\n-              <Heroicons.Outline.render icon=\"{m.icon}\" class=\"w-6 h-6 text-gray-500 flex-shrink-0 group-hover:text-gray-900 transition duration-75\" />\n+              <Heroicons.Outline.render icon=\"chart_pie\" class=\"w-6 h-6 text-gray-500 flex-shrink-0 group-hover:text-gray-900 transition duration-75\" />\n               <span class=\"ml-3\"><%= m.label %></span>\n             <% end %>\n           </li>\n           <% end %>\n"
                },
                {
                    "date": 1657832236999,
                    "content": "Index: \n===================================================================\n--- \n+++ \n@@ -22,9 +22,8 @@\n                   placeholder=\"Search\">\n               </div>\n             </form>\n           </li>\n-          <%= inspect menu() %>\n           <%= for m <- menu() do %>\n           <li>\n             <%= link to: m.route, class: \"text-base text-gray-900 font-normal rounded-lg hover:bg-gray-100 flex items-center p-2 group\" do %>\n               <Heroicons.Outline.render icon=\"chart_pie\" class=\"w-6 h-6 text-gray-500 flex-shrink-0 group-hover:text-gray-900 transition duration-75\" />\n"
                },
                {
                    "date": 1657832262525,
                    "content": "Index: \n===================================================================\n--- \n+++ \n@@ -25,9 +25,9 @@\n           </li>\n           <%= for m <- menu() do %>\n           <li>\n             <%= link to: m.route, class: \"text-base text-gray-900 font-normal rounded-lg hover:bg-gray-100 flex items-center p-2 group\" do %>\n-              <Heroicons.Outline.render icon=\"chart_pie\" class=\"w-6 h-6 text-gray-500 flex-shrink-0 group-hover:text-gray-900 transition duration-75\" />\n+              <Heroicons.Outline.render icon=\"m.icon\" class=\"w-6 h-6 text-gray-500 flex-shrink-0 group-hover:text-gray-900 transition duration-75\" />\n               <span class=\"ml-3\"><%= m.label %></span>\n             <% end %>\n           </li>\n           <% end %>\n"
                },
                {
                    "date": 1657832279208,
                    "content": "Index: \n===================================================================\n--- \n+++ \n@@ -25,9 +25,9 @@\n           </li>\n           <%= for m <- menu() do %>\n           <li>\n             <%= link to: m.route, class: \"text-base text-gray-900 font-normal rounded-lg hover:bg-gray-100 flex items-center p-2 group\" do %>\n-              <Heroicons.Outline.render icon=\"m.icon\" class=\"w-6 h-6 text-gray-500 flex-shrink-0 group-hover:text-gray-900 transition duration-75\" />\n+              <Heroicons.Outline.render icon=\"{@m.icon}\" class=\"w-6 h-6 text-gray-500 flex-shrink-0 group-hover:text-gray-900 transition duration-75\" />\n               <span class=\"ml-3\"><%= m.label %></span>\n             <% end %>\n           </li>\n           <% end %>\n"
                },
                {
                    "date": 1657832289747,
                    "content": "Index: \n===================================================================\n--- \n+++ \n@@ -25,9 +25,9 @@\n           </li>\n           <%= for m <- menu() do %>\n           <li>\n             <%= link to: m.route, class: \"text-base text-gray-900 font-normal rounded-lg hover:bg-gray-100 flex items-center p-2 group\" do %>\n-              <Heroicons.Outline.render icon=\"{@m.icon}\" class=\"w-6 h-6 text-gray-500 flex-shrink-0 group-hover:text-gray-900 transition duration-75\" />\n+              <Heroicons.Outline.render icon=\"{m.icon}\" class=\"w-6 h-6 text-gray-500 flex-shrink-0 group-hover:text-gray-900 transition duration-75\" />\n               <span class=\"ml-3\"><%= m.label %></span>\n             <% end %>\n           </li>\n           <% end %>\n"
                },
                {
                    "date": 1657832297224,
                    "content": "Index: \n===================================================================\n--- \n+++ \n@@ -25,9 +25,9 @@\n           </li>\n           <%= for m <- menu() do %>\n           <li>\n             <%= link to: m.route, class: \"text-base text-gray-900 font-normal rounded-lg hover:bg-gray-100 flex items-center p-2 group\" do %>\n-              <Heroicons.Outline.render icon=\"{m.icon}\" class=\"w-6 h-6 text-gray-500 flex-shrink-0 group-hover:text-gray-900 transition duration-75\" />\n+              <Heroicons.Outline.render icon={m.icon} class=\"w-6 h-6 text-gray-500 flex-shrink-0 group-hover:text-gray-900 transition duration-75\" />\n               <span class=\"ml-3\"><%= m.label %></span>\n             <% end %>\n           </li>\n           <% end %>\n"
                },
                {
                    "date": 1657832334704,
                    "content": "Index: \n===================================================================\n--- \n+++ \n@@ -30,92 +30,9 @@\n               <span class=\"ml-3\"><%= m.label %></span>\n             <% end %>\n           </li>\n           <% end %>\n-          <li>\n-            <%= link to: Routes.page_path(@conn, :index), class: \"text-base text-gray-900 font-normal rounded-lg hover:bg-gray-100 flex items-center p-2 group\" do %>\n-              <Heroicons.Outline.chart_pie class=\"w-6 h-6 text-gray-500 flex-shrink-0 group-hover:text-gray-900 transition duration-75\" />\n-              <span class=\"ml-3\">Dashboard</span>\n-            <% end %>\n-          </li>\n-          <li>\n-            <a href=\"https://demo.themesberg.com/windster-pro/kanban/\" target=\"_blank\"\n-              class=\"text-base text-gray-900 font-normal rounded-lg hover:bg-gray-100 flex items-center p-2 group \">\n-              <svg class=\"w-6 h-6 text-gray-500 flex-shrink-0 group-hover:text-gray-900 transition duration-75\"\n-                fill=\"currentColor\" viewBox=\"0 0 20 20\" xmlns=\"http://www.w3.org/2000/svg\">\n-                <path\n-                  d=\"M5 3a2 2 0 00-2 2v2a2 2 0 002 2h2a2 2 0 002-2V5a2 2 0 00-2-2H5zM5 11a2 2 0 00-2 2v2a2 2 0 002 2h2a2 2 0 002-2v-2a2 2 0 00-2-2H5zM11 5a2 2 0 012-2h2a2 2 0 012 2v2a2 2 0 01-2 2h-2a2 2 0 01-2-2V5zM11 13a2 2 0 012-2h2a2 2 0 012 2v2a2 2 0 01-2 2h-2a2 2 0 01-2-2v-2z\">\n-                </path>\n-              </svg>\n-              <span class=\"ml-3 flex-1 whitespace-nowrap\">Kanban</span>\n-              <span\n-                class=\"bg-gray-200 text-gray-800 ml-3 text-sm font-medium inline-flex items-center justify-center px-2 rounded-full\">Pro</span>\n-            </a>\n-          </li>\n-          <li>\n-            <a href=\"https://demo.themesberg.com/windster-pro/mailing/inbox/\" target=\"_blank\"\n-              class=\"text-base text-gray-900 font-normal rounded-lg hover:bg-gray-100 flex items-center p-2 group \">\n-              <svg class=\"w-6 h-6 text-gray-500 flex-shrink-0 group-hover:text-gray-900 transition duration-75\"\n-                fill=\"currentColor\" viewBox=\"0 0 20 20\" xmlns=\"http://www.w3.org/2000/svg\">\n-                <path\n-                  d=\"M8.707 7.293a1 1 0 00-1.414 1.414l2 2a1 1 0 001.414 0l2-2a1 1 0 00-1.414-1.414L11 7.586V3a1 1 0 10-2 0v4.586l-.293-.293z\">\n-                </path>\n-                <path\n-                  d=\"M3 5a2 2 0 012-2h1a1 1 0 010 2H5v7h2l1 2h4l1-2h2V5h-1a1 1 0 110-2h1a2 2 0 012 2v10a2 2 0 01-2 2H5a2 2 0 01-2-2V5z\">\n-                </path>\n-              </svg>\n-              <span class=\"ml-3 flex-1 whitespace-nowrap\">Inbox</span>\n-              <span\n-                class=\"bg-gray-200 text-gray-800 ml-3 text-sm font-medium inline-flex items-center justify-center px-2 rounded-full\">Pro</span>\n-            </a>\n-          </li>\n-          <li>\n-            <a href=\"https://demo.themesberg.com/windster/users/list/\"\n-              class=\"text-base text-gray-900 font-normal rounded-lg hover:bg-gray-100 flex items-center p-2 group \">\n-              <svg class=\"w-6 h-6 text-gray-500 flex-shrink-0 group-hover:text-gray-900 transition duration-75\"\n-                fill=\"currentColor\" viewBox=\"0 0 20 20\" xmlns=\"http://www.w3.org/2000/svg\">\n-                <path fill-rule=\"evenodd\" d=\"M10 9a3 3 0 100-6 3 3 0 000 6zm-7 9a7 7 0 1114 0H3z\" clip-rule=\"evenodd\">\n-                </path>\n-              </svg>\n-              <span class=\"ml-3 flex-1 whitespace-nowrap\">Users</span>\n-            </a>\n-          </li>\n-          <li>\n-            <a href=\"https://demo.themesberg.com/windster/e-commerce/products/\"\n-              class=\"text-base text-gray-900 font-normal rounded-lg hover:bg-gray-100 flex items-center p-2 group \">\n-              <svg class=\"w-6 h-6 text-gray-500 flex-shrink-0 group-hover:text-gray-900 transition duration-75\"\n-                fill=\"currentColor\" viewBox=\"0 0 20 20\" xmlns=\"http://www.w3.org/2000/svg\">\n-                <path fill-rule=\"evenodd\"\n-                  d=\"M10 2a4 4 0 00-4 4v1H5a1 1 0 00-.994.89l-1 9A1 1 0 004 18h12a1 1 0 00.994-1.11l-1-9A1 1 0 0015 7h-1V6a4 4 0 00-4-4zm2 5V6a2 2 0 10-4 0v1h4zm-6 3a1 1 0 112 0 1 1 0 01-2 0zm7-1a1 1 0 100 2 1 1 0 000-2z\"\n-                  clip-rule=\"evenodd\"></path>\n-              </svg>\n-              <span class=\"ml-3 flex-1 whitespace-nowrap\">Products</span>\n-            </a>\n-          </li>\n-          <li>\n-            <a href=\"https://demo.themesberg.com/windster/authentication/sign-in/\"\n-              class=\"text-base text-gray-900 font-normal rounded-lg hover:bg-gray-100 flex items-center p-2 group \">\n-              <svg class=\"w-6 h-6 text-gray-500 flex-shrink-0 group-hover:text-gray-900 transition duration-75\"\n-                fill=\"currentColor\" viewBox=\"0 0 20 20\" xmlns=\"http://www.w3.org/2000/svg\">\n-                <path fill-rule=\"evenodd\"\n-                  d=\"M3 3a1 1 0 00-1 1v12a1 1 0 102 0V4a1 1 0 00-1-1zm10.293 9.293a1 1 0 001.414 1.414l3-3a1 1 0 000-1.414l-3-3a1 1 0 10-1.414 1.414L14.586 9H7a1 1 0 100 2h7.586l-1.293 1.293z\"\n-                  clip-rule=\"evenodd\"></path>\n-              </svg>\n-              <span class=\"ml-3 flex-1 whitespace-nowrap\">Sign In</span>\n-            </a>\n-          </li>\n-          <li>\n-            <a href=\"https://demo.themesberg.com/windster/authentication/sign-up/\"\n-              class=\"text-base text-gray-900 font-normal rounded-lg hover:bg-gray-100 flex items-center p-2 group \">\n-              <svg class=\"w-6 h-6 text-gray-500 flex-shrink-0 group-hover:text-gray-900 transition duration-75\"\n-                fill=\"currentColor\" viewBox=\"0 0 20 20\" xmlns=\"http://www.w3.org/2000/svg\">\n-                <path fill-rule=\"evenodd\"\n-                  d=\"M5 4a3 3 0 00-3 3v6a3 3 0 003 3h10a3 3 0 003-3V7a3 3 0 00-3-3H5zm-1 9v-1h5v2H5a1 1 0 01-1-1zm7 1h4a1 1 0 001-1v-1h-5v2zm0-4h5V8h-5v2zM9 8H4v2h5V8z\"\n-                  clip-rule=\"evenodd\"></path>\n-              </svg>\n-              <span class=\"ml-3 flex-1 whitespace-nowrap\">Sign Up</span>\n-            </a>\n-          </li>\n+          \n         </ul>\n         <div class=\"space-y-2 pt-2\">\n           <a href=\"https://demo.themesberg.com/windster/pricing/\"\n             class=\"text-base text-gray-900 font-normal rounded-lg hover:bg-gray-100 group transition duration-75 flex items-center p-2\">\n"
                },
                {
                    "date": 1657832367026,
                    "content": "Index: \n===================================================================\n--- \n+++ \n@@ -33,50 +33,9 @@\n           <% end %>\n           \n         </ul>\n         <div class=\"space-y-2 pt-2\">\n-          <a href=\"https://demo.themesberg.com/windster/pricing/\"\n-            class=\"text-base text-gray-900 font-normal rounded-lg hover:bg-gray-100 group transition duration-75 flex items-center p-2\">\n-            <svg class=\"w-5 h-5 text-gray-500 flex-shrink-0 group-hover:text-gray-900 transition duration-75\"\n-              aria-hidden=\"true\" focusable=\"false\" data-prefix=\"fas\" data-icon=\"gem\" role=\"img\"\n-              xmlns=\"http://www.w3.org/2000/svg\" viewBox=\"0 0 512 512\">\n-              <path fill=\"currentColor\"\n-                d=\"M378.7 32H133.3L256 182.7L378.7 32zM512 192l-107.4-141.3L289.6 192H512zM107.4 50.67L0 192h222.4L107.4 50.67zM244.3 474.9C247.3 478.2 251.6 480 256 480s8.653-1.828 11.67-5.062L510.6 224H1.365L244.3 474.9z\">\n-              </path>\n-            </svg>\n-            <span class=\"ml-4\">Upgrade to Pro</span>\n-          </a>\n-          <a href=\"https://flowbite.com/docs/getting-started/introduction/\" target=\"_blank\"\n-            class=\"text-base text-gray-900 font-normal rounded-lg hover:bg-gray-100 group transition duration-75 flex items-center p-2\">\n-            <svg class=\"w-6 h-6 text-gray-500 flex-shrink-0 group-hover:text-gray-900 transition duration-75\"\n-              fill=\"currentColor\" viewBox=\"0 0 20 20\" xmlns=\"http://www.w3.org/2000/svg\">\n-              <path d=\"M9 2a1 1 0 000 2h2a1 1 0 100-2H9z\"></path>\n-              <path fill-rule=\"evenodd\"\n-                d=\"M4 5a2 2 0 012-2 3 3 0 003 3h2a3 3 0 003-3 2 2 0 012 2v11a2 2 0 01-2 2H6a2 2 0 01-2-2V5zm3 4a1 1 0 000 2h.01a1 1 0 100-2H7zm3 0a1 1 0 000 2h3a1 1 0 100-2h-3zm-3 4a1 1 0 100 2h.01a1 1 0 100-2H7zm3 0a1 1 0 100 2h3a1 1 0 100-2h-3z\"\n-                clip-rule=\"evenodd\"></path>\n-            </svg>\n-            <span class=\"ml-3\">Documentation</span>\n-          </a>\n-          <a href=\"https://flowbite.com/docs/components/alerts/\" target=\"_blank\"\n-            class=\"text-base text-gray-900 font-normal rounded-lg hover:bg-gray-100 group transition duration-75 flex items-center p-2\">\n-            <svg class=\"w-6 h-6 text-gray-500 flex-shrink-0 group-hover:text-gray-900 transition duration-75\"\n-              fill=\"currentColor\" viewBox=\"0 0 20 20\" xmlns=\"http://www.w3.org/2000/svg\">\n-              <path\n-                d=\"M7 3a1 1 0 000 2h6a1 1 0 100-2H7zM4 7a1 1 0 011-1h10a1 1 0 110 2H5a1 1 0 01-1-1zM2 11a2 2 0 012-2h12a2 2 0 012 2v4a2 2 0 01-2 2H4a2 2 0 01-2-2v-4z\">\n-              </path>\n-            </svg>\n-            <span class=\"ml-3\">Components</span>\n-          </a>\n-          <a href=\"https://github.com/themesberg/windster-tailwind-css-dashboard/issues\" target=\"_blank\"\n-            class=\"text-base text-gray-900 font-normal rounded-lg hover:bg-gray-100 group transition duration-75 flex items-center p-2\">\n-            <svg class=\"w-6 h-6 text-gray-500 flex-shrink-0 group-hover:text-gray-900 transition duration-75\"\n-              fill=\"currentColor\" viewBox=\"0 0 20 20\" xmlns=\"http://www.w3.org/2000/svg\">\n-              <path fill-rule=\"evenodd\"\n-                d=\"M18 10a8 8 0 11-16 0 8 8 0 0116 0zm-2 0c0 .993-.241 1.929-.668 2.754l-1.524-1.525a3.997 3.997 0 00.078-2.183l1.562-1.562C15.802 8.249 16 9.1 16 10zm-5.165 3.913l1.58 1.58A5.98 5.98 0 0110 16a5.976 5.976 0 01-2.516-.552l1.562-1.562a4.006 4.006 0 001.789.027zm-4.677-2.796a4.002 4.002 0 01-.041-2.08l-.08.08-1.53-1.533A5.98 5.98 0 004 10c0 .954.223 1.856.619 2.657l1.54-1.54zm1.088-6.45A5.974 5.974 0 0110 4c.954 0 1.856.223 2.657.619l-1.54 1.54a4.002 4.002 0 00-2.346.033L7.246 4.668zM12 10a2 2 0 11-4 0 2 2 0 014 0z\"\n-                clip-rule=\"evenodd\"></path>\n-            </svg>\n-            <span class=\"ml-3\">Help</span>\n-          </a>\n+          \n         </div>\n       </div>\n     </div>\n   </div>\n"
                }
            ],
            "date": 1657804231876,
            "name": "Commit-0",
            "content": "<aside id=\"sidebar\"\n  class=\"fixed hidden z-20 h-full top-0 left-0 pt-16 flex lg:flex flex-shrink-0 flex-col w-64 transition-width duration-75\"\n  aria-label=\"Sidebar\">\n  <div class=\"relative flex-1 flex flex-col min-h-0 border-r border-gray-200 bg-white pt-0\">\n    <div class=\"flex-1 flex flex-col pt-5 pb-4 overflow-y-auto\">\n      <div class=\"flex-1 px-3 bg-white divide-y space-y-1\">\n        <ul class=\"space-y-2 pb-2\">\n          <li>\n            <form action=\"#\" method=\"GET\" class=\"lg:hidden\">\n              <label for=\"mobile-search\" class=\"sr-only\">Search</label>\n              <div class=\"relative\">\n                <div class=\"absolute inset-y-0 left-0 pl-3 flex items-center pointer-events-none\">\n                  <svg class=\"w-5 h-5 text-gray-500\" fill=\"currentColor\" viewBox=\"0 0 20 20\"\n                    xmlns=\"http://www.w3.org/2000/svg\">\n                    <path\n                      d=\"M5 3a2 2 0 00-2 2v2a2 2 0 002 2h2a2 2 0 002-2V5a2 2 0 00-2-2H5zM5 11a2 2 0 00-2 2v2a2 2 0 002 2h2a2 2 0 002-2v-2a2 2 0 00-2-2H5zM11 5a2 2 0 012-2h2a2 2 0 012 2v2a2 2 0 01-2 2h-2a2 2 0 01-2-2V5zM11 13a2 2 0 012-2h2a2 2 0 012 2v2a2 2 0 01-2 2h-2a2 2 0 01-2-2v-2z\">\n                    </path>\n                  </svg>\n                </div>\n                <input type=\"text\" name=\"email\" id=\"mobile-search\"\n                  class=\"bg-gray-50 border border-gray-300 text-gray-900 text-sm rounded-lg focus:ring-cyan-600 focus:ring-cyan-600 block w-full pl-10 p-2.5\"\n                  placeholder=\"Search\">\n              </div>\n            </form>\n          </li>\n          <li>\n            <%= link to: Routes.page_path(@conn, :index), class: \"text-base text-gray-900 font-normal rounded-lg flex items-center p-2 hover:bg-gray-100 group\" do %>\n                <span class=\"self-center whitespace-nowrap\">\n                    <span class=\"text-amber-500\">Optimal</span>\n                    <span>Finder</span>\n                </span>\n            <% end %>\n            <a href=\"https://demo.themesberg.com/windster/\"\n              class=\"text-base text-gray-900 font-normal rounded-lg flex items-center p-2 hover:bg-gray-100 group\">\n              <svg class=\"w-6 h-6 text-gray-500 group-hover:text-gray-900 transition duration-75\" fill=\"currentColor\"\n                viewBox=\"0 0 20 20\" xmlns=\"http://www.w3.org/2000/svg\">\n                <path d=\"M2 10a8 8 0 018-8v8h8a8 8 0 11-16 0z\"></path>\n                <path d=\"M12 2.252A8.014 8.014 0 0117.748 8H12V2.252z\"></path>\n              </svg>\n              <span class=\"ml-3\">Dashboard</span>\n            </a>\n          </li>\n          <li>\n            <a href=\"https://demo.themesberg.com/windster-pro/kanban/\" target=\"_blank\"\n              class=\"text-base text-gray-900 font-normal rounded-lg hover:bg-gray-100 flex items-center p-2 group \">\n              <svg class=\"w-6 h-6 text-gray-500 flex-shrink-0 group-hover:text-gray-900 transition duration-75\"\n                fill=\"currentColor\" viewBox=\"0 0 20 20\" xmlns=\"http://www.w3.org/2000/svg\">\n                <path\n                  d=\"M5 3a2 2 0 00-2 2v2a2 2 0 002 2h2a2 2 0 002-2V5a2 2 0 00-2-2H5zM5 11a2 2 0 00-2 2v2a2 2 0 002 2h2a2 2 0 002-2v-2a2 2 0 00-2-2H5zM11 5a2 2 0 012-2h2a2 2 0 012 2v2a2 2 0 01-2 2h-2a2 2 0 01-2-2V5zM11 13a2 2 0 012-2h2a2 2 0 012 2v2a2 2 0 01-2 2h-2a2 2 0 01-2-2v-2z\">\n                </path>\n              </svg>\n              <span class=\"ml-3 flex-1 whitespace-nowrap\">Kanban</span>\n              <span\n                class=\"bg-gray-200 text-gray-800 ml-3 text-sm font-medium inline-flex items-center justify-center px-2 rounded-full\">Pro</span>\n            </a>\n          </li>\n          <li>\n            <a href=\"https://demo.themesberg.com/windster-pro/mailing/inbox/\" target=\"_blank\"\n              class=\"text-base text-gray-900 font-normal rounded-lg hover:bg-gray-100 flex items-center p-2 group \">\n              <svg class=\"w-6 h-6 text-gray-500 flex-shrink-0 group-hover:text-gray-900 transition duration-75\"\n                fill=\"currentColor\" viewBox=\"0 0 20 20\" xmlns=\"http://www.w3.org/2000/svg\">\n                <path\n                  d=\"M8.707 7.293a1 1 0 00-1.414 1.414l2 2a1 1 0 001.414 0l2-2a1 1 0 00-1.414-1.414L11 7.586V3a1 1 0 10-2 0v4.586l-.293-.293z\">\n                </path>\n                <path\n                  d=\"M3 5a2 2 0 012-2h1a1 1 0 010 2H5v7h2l1 2h4l1-2h2V5h-1a1 1 0 110-2h1a2 2 0 012 2v10a2 2 0 01-2 2H5a2 2 0 01-2-2V5z\">\n                </path>\n              </svg>\n              <span class=\"ml-3 flex-1 whitespace-nowrap\">Inbox</span>\n              <span\n                class=\"bg-gray-200 text-gray-800 ml-3 text-sm font-medium inline-flex items-center justify-center px-2 rounded-full\">Pro</span>\n            </a>\n          </li>\n          <li>\n            <a href=\"https://demo.themesberg.com/windster/users/list/\"\n              class=\"text-base text-gray-900 font-normal rounded-lg hover:bg-gray-100 flex items-center p-2 group \">\n              <svg class=\"w-6 h-6 text-gray-500 flex-shrink-0 group-hover:text-gray-900 transition duration-75\"\n                fill=\"currentColor\" viewBox=\"0 0 20 20\" xmlns=\"http://www.w3.org/2000/svg\">\n                <path fill-rule=\"evenodd\" d=\"M10 9a3 3 0 100-6 3 3 0 000 6zm-7 9a7 7 0 1114 0H3z\" clip-rule=\"evenodd\">\n                </path>\n              </svg>\n              <span class=\"ml-3 flex-1 whitespace-nowrap\">Users</span>\n            </a>\n          </li>\n          <li>\n            <a href=\"https://demo.themesberg.com/windster/e-commerce/products/\"\n              class=\"text-base text-gray-900 font-normal rounded-lg hover:bg-gray-100 flex items-center p-2 group \">\n              <svg class=\"w-6 h-6 text-gray-500 flex-shrink-0 group-hover:text-gray-900 transition duration-75\"\n                fill=\"currentColor\" viewBox=\"0 0 20 20\" xmlns=\"http://www.w3.org/2000/svg\">\n                <path fill-rule=\"evenodd\"\n                  d=\"M10 2a4 4 0 00-4 4v1H5a1 1 0 00-.994.89l-1 9A1 1 0 004 18h12a1 1 0 00.994-1.11l-1-9A1 1 0 0015 7h-1V6a4 4 0 00-4-4zm2 5V6a2 2 0 10-4 0v1h4zm-6 3a1 1 0 112 0 1 1 0 01-2 0zm7-1a1 1 0 100 2 1 1 0 000-2z\"\n                  clip-rule=\"evenodd\"></path>\n              </svg>\n              <span class=\"ml-3 flex-1 whitespace-nowrap\">Products</span>\n            </a>\n          </li>\n          <li>\n            <a href=\"https://demo.themesberg.com/windster/authentication/sign-in/\"\n              class=\"text-base text-gray-900 font-normal rounded-lg hover:bg-gray-100 flex items-center p-2 group \">\n              <svg class=\"w-6 h-6 text-gray-500 flex-shrink-0 group-hover:text-gray-900 transition duration-75\"\n                fill=\"currentColor\" viewBox=\"0 0 20 20\" xmlns=\"http://www.w3.org/2000/svg\">\n                <path fill-rule=\"evenodd\"\n                  d=\"M3 3a1 1 0 00-1 1v12a1 1 0 102 0V4a1 1 0 00-1-1zm10.293 9.293a1 1 0 001.414 1.414l3-3a1 1 0 000-1.414l-3-3a1 1 0 10-1.414 1.414L14.586 9H7a1 1 0 100 2h7.586l-1.293 1.293z\"\n                  clip-rule=\"evenodd\"></path>\n              </svg>\n              <span class=\"ml-3 flex-1 whitespace-nowrap\">Sign In</span>\n            </a>\n          </li>\n          <li>\n            <a href=\"https://demo.themesberg.com/windster/authentication/sign-up/\"\n              class=\"text-base text-gray-900 font-normal rounded-lg hover:bg-gray-100 flex items-center p-2 group \">\n              <svg class=\"w-6 h-6 text-gray-500 flex-shrink-0 group-hover:text-gray-900 transition duration-75\"\n                fill=\"currentColor\" viewBox=\"0 0 20 20\" xmlns=\"http://www.w3.org/2000/svg\">\n                <path fill-rule=\"evenodd\"\n                  d=\"M5 4a3 3 0 00-3 3v6a3 3 0 003 3h10a3 3 0 003-3V7a3 3 0 00-3-3H5zm-1 9v-1h5v2H5a1 1 0 01-1-1zm7 1h4a1 1 0 001-1v-1h-5v2zm0-4h5V8h-5v2zM9 8H4v2h5V8z\"\n                  clip-rule=\"evenodd\"></path>\n              </svg>\n              <span class=\"ml-3 flex-1 whitespace-nowrap\">Sign Up</span>\n            </a>\n          </li>\n        </ul>\n        <div class=\"space-y-2 pt-2\">\n          <a href=\"https://demo.themesberg.com/windster/pricing/\"\n            class=\"text-base text-gray-900 font-normal rounded-lg hover:bg-gray-100 group transition duration-75 flex items-center p-2\">\n            <svg class=\"w-5 h-5 text-gray-500 flex-shrink-0 group-hover:text-gray-900 transition duration-75\"\n              aria-hidden=\"true\" focusable=\"false\" data-prefix=\"fas\" data-icon=\"gem\" role=\"img\"\n              xmlns=\"http://www.w3.org/2000/svg\" viewBox=\"0 0 512 512\">\n              <path fill=\"currentColor\"\n                d=\"M378.7 32H133.3L256 182.7L378.7 32zM512 192l-107.4-141.3L289.6 192H512zM107.4 50.67L0 192h222.4L107.4 50.67zM244.3 474.9C247.3 478.2 251.6 480 256 480s8.653-1.828 11.67-5.062L510.6 224H1.365L244.3 474.9z\">\n              </path>\n            </svg>\n            <span class=\"ml-4\">Upgrade to Pro</span>\n          </a>\n          <a href=\"https://flowbite.com/docs/getting-started/introduction/\" target=\"_blank\"\n            class=\"text-base text-gray-900 font-normal rounded-lg hover:bg-gray-100 group transition duration-75 flex items-center p-2\">\n            <svg class=\"w-6 h-6 text-gray-500 flex-shrink-0 group-hover:text-gray-900 transition duration-75\"\n              fill=\"currentColor\" viewBox=\"0 0 20 20\" xmlns=\"http://www.w3.org/2000/svg\">\n              <path d=\"M9 2a1 1 0 000 2h2a1 1 0 100-2H9z\"></path>\n              <path fill-rule=\"evenodd\"\n                d=\"M4 5a2 2 0 012-2 3 3 0 003 3h2a3 3 0 003-3 2 2 0 012 2v11a2 2 0 01-2 2H6a2 2 0 01-2-2V5zm3 4a1 1 0 000 2h.01a1 1 0 100-2H7zm3 0a1 1 0 000 2h3a1 1 0 100-2h-3zm-3 4a1 1 0 100 2h.01a1 1 0 100-2H7zm3 0a1 1 0 100 2h3a1 1 0 100-2h-3z\"\n                clip-rule=\"evenodd\"></path>\n            </svg>\n            <span class=\"ml-3\">Documentation</span>\n          </a>\n          <a href=\"https://flowbite.com/docs/components/alerts/\" target=\"_blank\"\n            class=\"text-base text-gray-900 font-normal rounded-lg hover:bg-gray-100 group transition duration-75 flex items-center p-2\">\n            <svg class=\"w-6 h-6 text-gray-500 flex-shrink-0 group-hover:text-gray-900 transition duration-75\"\n              fill=\"currentColor\" viewBox=\"0 0 20 20\" xmlns=\"http://www.w3.org/2000/svg\">\n              <path\n                d=\"M7 3a1 1 0 000 2h6a1 1 0 100-2H7zM4 7a1 1 0 011-1h10a1 1 0 110 2H5a1 1 0 01-1-1zM2 11a2 2 0 012-2h12a2 2 0 012 2v4a2 2 0 01-2 2H4a2 2 0 01-2-2v-4z\">\n              </path>\n            </svg>\n            <span class=\"ml-3\">Components</span>\n          </a>\n          <a href=\"https://github.com/themesberg/windster-tailwind-css-dashboard/issues\" target=\"_blank\"\n            class=\"text-base text-gray-900 font-normal rounded-lg hover:bg-gray-100 group transition duration-75 flex items-center p-2\">\n            <svg class=\"w-6 h-6 text-gray-500 flex-shrink-0 group-hover:text-gray-900 transition duration-75\"\n              fill=\"currentColor\" viewBox=\"0 0 20 20\" xmlns=\"http://www.w3.org/2000/svg\">\n              <path fill-rule=\"evenodd\"\n                d=\"M18 10a8 8 0 11-16 0 8 8 0 0116 0zm-2 0c0 .993-.241 1.929-.668 2.754l-1.524-1.525a3.997 3.997 0 00.078-2.183l1.562-1.562C15.802 8.249 16 9.1 16 10zm-5.165 3.913l1.58 1.58A5.98 5.98 0 0110 16a5.976 5.976 0 01-2.516-.552l1.562-1.562a4.006 4.006 0 001.789.027zm-4.677-2.796a4.002 4.002 0 01-.041-2.08l-.08.08-1.53-1.533A5.98 5.98 0 004 10c0 .954.223 1.856.619 2.657l1.54-1.54zm1.088-6.45A5.974 5.974 0 0110 4c.954 0 1.856.223 2.657.619l-1.54 1.54a4.002 4.002 0 00-2.346.033L7.246 4.668zM12 10a2 2 0 11-4 0 2 2 0 014 0z\"\n                clip-rule=\"evenodd\"></path>\n            </svg>\n            <span class=\"ml-3\">Help</span>\n          </a>\n        </div>\n      </div>\n    </div>\n  </div>\n</aside>"
        }
    ]
}